setup.py
aghajani_learn_1/Binomialdistribution.py
aghajani_learn_1/Gaussiandistribution.py
aghajani_learn_1/Generaldistribution.py
aghajani_learn_1/__init__.py
aghajani_learn_1.egg-info/PKG-INFO
aghajani_learn_1.egg-info/SOURCES.txt
aghajani_learn_1.egg-info/dependency_links.txt
aghajani_learn_1.egg-info/not-zip-safe
aghajani_learn_1.egg-info/top_level.txt